entity_event/__init__.py
entity_event/admin.py
entity_event/apps.py
entity_event/context_loader.py
entity_event/context_serializer.py
entity_event/models.py
entity_event/urls.py
entity_event/version.py
entity_event/migrations/0001_0005_squashed.py
entity_event/migrations/__init__.py
entity_event/tests/__init__.py
entity_event/tests/admin_tests.py
entity_event/tests/context_loader_tests.py
entity_event/tests/context_serializer_tests.py
entity_event/tests/model_tests.py
entity_event/tests/models.py
entity_event/tests/migrations/0001_initial.py
entity_event/tests/migrations/__init__.py
django_entity_event-3.1.0.dist-info/LICENSE
django_entity_event-3.1.0.dist-info/METADATA
django_entity_event-3.1.0.dist-info/WHEEL
django_entity_event-3.1.0.dist-info/top_level.txt
django_entity_event-3.1.0.dist-info/RECORD
