Metadata-Version: 2.1
Name: django-entity-event
Version: 3.1.0
Summary: Newsfeed-style event tracking and subscription management for django-entity.
Home-page: https://github.com/ambitioninc/django-entity-event
Author: Erik Swanson
Author-email: opensource@ambition.com
License: MIT
Classifier: Programming Language :: Python
Classifier: Programming Language :: Python :: 3.7
Classifier: Programming Language :: Python :: 3.8
Classifier: Programming Language :: Python :: 3.9
Classifier: Intended Audience :: Developers
Classifier: License :: OSI Approved :: MIT License
Classifier: Operating System :: OS Independent
Classifier: Framework :: Django
Classifier: Framework :: Django :: 3.2
Classifier: Framework :: Django :: 4.0
Classifier: Framework :: Django :: 4.1
Classifier: Framework :: Django :: 4.2
License-File: LICENSE
Requires-Dist: cached-property (>=1.3.1)
Requires-Dist: django-entity (>=6.1.0)
